cv_cli/__init__.py
cv_cli/cli.py
cv_cli/constants.py
cv_cli/git.py
cv_cli/io.py
cv_cli/profiles.py
cv_cli/render.py
cv_cli/templates.py
cv_cli-1.1.0.dist-info/METADATA
cv_cli-1.1.0.dist-info/WHEEL
cv_cli-1.1.0.dist-info/entry_points.txt
cv_cli-1.1.0.dist-info/licenses/LICENSE
cv_cli-1.1.0.dist-info/RECORD
