Metadata-Version: 2.4
Name: cv-cli
Version: 1.1.0
Summary: Command-line tool to generate resumes from YAML and LaTeX templates
Author-email: Daniel Castro <dcastro@ualberta.ca>
License: MIT
License-File: LICENSE
Requires-Python: >=3.8
Requires-Dist: colorama==0.4.6
Requires-Dist: jinja2==3.1.6
Requires-Dist: markupsafe==3.0.2
Requires-Dist: packaging==25.0
Requires-Dist: pyyaml==6.0.2
Requires-Dist: watchdog==6.0.0
Provides-Extra: dev
Requires-Dist: coverage==7.8.2; extra == 'dev'
Requires-Dist: iniconfig==2.1.0; extra == 'dev'
Requires-Dist: pluggy==1.6.0; extra == 'dev'
Requires-Dist: pytest-cov==6.1.1; extra == 'dev'
Requires-Dist: pytest==8.3.5; extra == 'dev'
